dream_toolbox/__init__.py
dream_toolbox/cache/__init__.py
dream_toolbox/cache/cache.py
dream_toolbox/database/fassi_vdb.py
dream_toolbox/database/sqlite_db.py
dream_toolbox/dataclass/__init__.py
dream_toolbox/dataclass/base_dataclass.py
dream_toolbox/openai/__init__.py
dream_toolbox/openai/openai_api.py
dream_toolbox/retry/__init__.py
dream_toolbox/retry/retry.py
dream_toolbox/utils/__init__.py
dream_toolbox/utils/utils.py
dream_toolbox-0.1.1.dist-info/licenses/LICENSE
dream_toolbox-0.1.1.dist-info/METADATA
dream_toolbox-0.1.1.dist-info/WHEEL
dream_toolbox-0.1.1.dist-info/top_level.txt
dream_toolbox-0.1.1.dist-info/RECORD
