Metadata-Version: 2.4
Name: dream_toolbox
Version: 0.1.1
Summary: Multifunctional tool kit
Author-email: MZ chen <hyhpchenmengzhu@gmail.com>
License-Expression: MIT
Project-URL: Homepage, https://github.com/VMIJUNV/dream_toolbox
Requires-Python: >=3.8
License-File: LICENSE
Dynamic: license-file
